dss_python_backend.libs/libdss_capid-08250188.so
dss_python_backend.libs/libdss_capi-5280ce98.so
dss_python_backend.libs/libklusolvex-39b5efc9.so
dss_python_backend-0.14.5.dist-info/RECORD
dss_python_backend-0.14.5.dist-info/METADATA
dss_python_backend-0.14.5.dist-info/WHEEL
dss_python_backend-0.14.5.dist-info/top_level.txt
dss_python_backend-0.14.5.dist-info/LICENSE
dss_python_backend/events.py
dss_python_backend/enums.py
dss_python_backend/__init__.py
dss_python_backend/_dss_capid.abi3.so
dss_python_backend/_dss_GenUserModel.abi3.so
dss_python_backend/_dss_capi.abi3.so
dss_python_backend/include/dss_capi.h
dss_python_backend/include/dss_classic.hpp
dss_python_backend/include/dss_UserModels.h
dss_python_backend/include/dss_CapUserControl.h
dss_python_backend/include/dss_common.hpp
dss_python_backend/include/dss_StoreDynaModel.h
dss_python_backend/include/dss.hpp
dss_python_backend/include/dss_capi_ctx.h
dss_python_backend/include/dss_GenUserModel.h
dss_python_backend/include/dss_obj.hpp
dss_python_backend/include/dss_StoreUserModel.h
dss_python_backend/include/dss_PVSystemUserModel.h
