Metadata-Version: 2.1
Name: dss-python-backend
Version: 0.14.5
Summary: Low-level Python bindings and native libs for DSS-Python. Not intended for direct usage, see DSS-Python instead.
Home-page: https://github.com/dss-extensions/dss_python_backend/
Author: Paulo Meira
Author-email: pmeira@ieee.org
License: BSD
Classifier: Intended Audience :: Science/Research
Classifier: Intended Audience :: Education
Classifier: Programming Language :: Python :: 3.7
Classifier: Programming Language :: Python :: 3.8
Classifier: Programming Language :: Python :: 3.9
Classifier: Programming Language :: Python :: 3.10
Classifier: Programming Language :: Python :: 3.11
Classifier: Programming Language :: Python :: 3.12
Classifier: Programming Language :: Python :: Implementation :: CPython
Classifier: Programming Language :: Python :: Implementation :: PyPy
Classifier: Development Status :: 5 - Production/Stable
Classifier: Topic :: Scientific/Engineering
Classifier: License :: OSI Approved :: BSD License
License-File: LICENSE
Requires-Dist: cffi >=1.11.2
